<?xml version="1.0" encoding="utf-8"?>
<Root>
	<AsteroidPosition x ="0.6781139" y ="-39.93015" />
		<PerlinValue>0.3964391</PerlinValue>
	<AsteroidPosition x ="-0.002087593" y ="-39.59222" />
		<PerlinValue>0.3782192</PerlinValue>
	<AsteroidPosition x ="0.5719404" y ="-39.04515" />
		<PerlinValue>0.3692357</PerlinValue>
	<AsteroidPosition x ="-1.148122" y ="-38.39729" />
		<PerlinValue>0.363326</PerlinValue>
	<AsteroidPosition x ="0.04877472" y ="-36.97747" />
		<PerlinValue>0.34883</PerlinValue>
	<AsteroidPosition x ="-0.08941364" y ="-35.25891" />
		<PerlinValue>0.3254266</PerlinValue>
	<AsteroidPosition x ="-0.6390657" y ="-33.47908" />
		<PerlinValue>0.3043812</PerlinValue>
	<AsteroidPosition x ="-1.052464" y ="-32.79289" />
		<PerlinValue>0.2991248</PerlinValue>
	<AsteroidPosition x ="-0.232111" y ="-33.09848" />
		<PerlinValue>0.3187553</PerlinValue>
	<AsteroidPosition x ="-1.178888" y ="-30.42623" />
		<PerlinValue>0.3646691</PerlinValue>
	<AsteroidPosition x ="1.694613" y ="-38.50021" />
		<PerlinValue>0</PerlinValue>
	<AsteroidPosition x ="0.1254845" y ="-37.771" />
		<PerlinValue>0.3984732</PerlinValue>
	<AsteroidPosition x ="0.8409395" y ="-36.75898" />
		<PerlinValue>0.3944828</PerlinValue>
	<AsteroidPosition x ="1.26386" y ="-37.08125" />
		<PerlinValue>0.392482</PerlinValue>
	<AsteroidPosition x ="0.8469296" y ="-35.18115" />
		<PerlinValue>0.3793229</PerlinValue>
	<AsteroidPosition x ="0.2561016" y ="-34.88776" />
		<PerlinValue>0.3520004</PerlinValue>
	<AsteroidPosition x ="-0.14713" y ="-34.05908" />
		<PerlinValue>0.3210213</PerlinValue>
	<AsteroidPosition x ="1.559815" y ="-32.49213" />
		<PerlinValue>0.3008206</PerlinValue>
	<AsteroidPosition x ="1.046274" y ="-31.69093" />
		<PerlinValue>0.3028407</PerlinValue>
	<AsteroidPosition x ="0.6377544" y ="-30.42315" />
		<PerlinValue>0.331568</PerlinValue>
	<AsteroidPosition x ="1.654946" y ="-34.9081" />
		<PerlinValue>0</PerlinValue>
	<AsteroidPosition x ="2.52635" y ="-35.29614" />
		<PerlinValue>0</PerlinValue>
	<AsteroidPosition x ="1.14391" y ="-32.59197" />
		<PerlinValue>0.3978498</PerlinValue>
	<AsteroidPosition x ="2.1984" y ="-32.45628" />
		<PerlinValue>0.3503022</PerlinValue>
	<AsteroidPosition x ="1.400503" y ="-32.04631" />
		<PerlinValue>0.3084044</PerlinValue>
	<AsteroidPosition x ="1.688675" y ="-31.09558" />
		<PerlinValue>0.2868795</PerlinValue>
	<AsteroidPosition x ="1.087355" y ="-29.90042" />
		<PerlinValue>0.2939715</PerlinValue>
	<AsteroidPosition x ="2.352457" y ="-34.671" />
		<PerlinValue>0</PerlinValue>
	<AsteroidPosition x ="2.46808" y ="-32.9189" />
		<PerlinValue>0</PerlinValue>
	<AsteroidPosition x ="2.269512" y ="-32.68975" />
		<PerlinValue>0</PerlinValue>
	<AsteroidPosition x ="3.533154" y ="-31.25331" />
		<PerlinValue>0.3822227</PerlinValue>
	<AsteroidPosition x ="2.581411" y ="-29.44375" />
		<PerlinValue>0.316423</PerlinValue>
	<AsteroidPosition x ="2.606837" y ="-28.91086" />
		<PerlinValue>0.2695182</PerlinValue>
	<AsteroidPosition x ="3.574267" y ="-28.39576" />
		<PerlinValue>0.253691</PerlinValue>
	<AsteroidPosition x ="3.111882" y ="-51.16032" />
		<PerlinValue>0.3818738</PerlinValue>
	<AsteroidPosition x ="3.727923" y ="-50.31849" />
		<PerlinValue>0</PerlinValue>
	<AsteroidPosition x ="3.71841" y ="-48.66809" />
		<PerlinValue>0</PerlinValue>
	<AsteroidPosition x ="3.716551" y ="-46.66562" />
		<PerlinValue>0</PerlinValue>
	<AsteroidPosition x ="4.312304" y ="-45.67019" />
		<PerlinValue>0.3817236</PerlinValue>
	<AsteroidPosition x ="4.7026" y ="-46.07938" />
		<PerlinValue>0.3397631</PerlinValue>
	<AsteroidPosition x ="3.882805" y ="-44.48233" />
		<PerlinValue>0.3254752</PerlinValue>
	<AsteroidPosition x ="3.772421" y ="-33.68658" />
		<PerlinValue>0</PerlinValue>
	<AsteroidPosition x ="4.405534" y ="-33.22162" />
		<PerlinValue>0</PerlinValue>
	<AsteroidPosition x ="4.207744" y ="-32.31763" />
		<PerlinValue>0</PerlinValue>
	<AsteroidPosition x ="4.596723" y ="-30.75612" />
		<PerlinValue>0</PerlinValue>
	<AsteroidPosition x ="3.667287" y ="-29.57131" />
		<PerlinValue>0.3096694</PerlinValue>
	<AsteroidPosition x ="4.596905" y ="-28.12925" />
		<PerlinValue>0.2368096</PerlinValue>
	<AsteroidPosition x ="4.714277" y ="-27.79781" />
		<PerlinValue>0.1982472</PerlinValue>
	<AsteroidPosition x ="4.954357" y ="-50.63081" />
		<PerlinValue>0.2001045</PerlinValue>
	<AsteroidPosition x ="5.700473" y ="-51.3247" />
		<PerlinValue>0.2377902</PerlinValue>
	<AsteroidPosition x ="4.109114" y ="-49.90253" />
		<PerlinValue>0.2982162</PerlinValue>
	<AsteroidPosition x ="5.64761" y ="-48.90839" />
		<PerlinValue>0.3655163</PerlinValue>
	<AsteroidPosition x ="4.68147" y ="-47.58491" />
		<PerlinValue>0</PerlinValue>
	<AsteroidPosition x ="4.462384" y ="-46.36133" />
		<PerlinValue>0.3570215</PerlinValue>
	<AsteroidPosition x ="5.372003" y ="-46.36219" />
		<PerlinValue>0.2916739</PerlinValue>
	<AsteroidPosition x ="3.897418" y ="-45.23515" />
		<PerlinValue>0.2499246</PerlinValue>
	<AsteroidPosition x ="4.639336" y ="-33.63959" />
		<PerlinValue>0</PerlinValue>
	<AsteroidPosition x ="4.849143" y ="-33.01039" />
		<PerlinValue>0</PerlinValue>
	<AsteroidPosition x ="4.118668" y ="-33.17945" />
		<PerlinValue>0</PerlinValue>
	<AsteroidPosition x ="3.828375" y ="-30.8463" />
		<PerlinValue>0</PerlinValue>
	<AsteroidPosition x ="4.296967" y ="-29.79573" />
		<PerlinValue>0</PerlinValue>
	<AsteroidPosition x ="5.502523" y ="-29.90545" />
		<PerlinValue>0.3963146</PerlinValue>
	<AsteroidPosition x ="3.917898" y ="-28.79796" />
		<PerlinValue>0.2817613</PerlinValue>
	<AsteroidPosition x ="4.069735" y ="-28.21678" />
		<PerlinValue>0.1865236</PerlinValue>
	<AsteroidPosition x ="6.072493" y ="-52.20429" />
		<PerlinValue>0.129581</PerlinValue>
	<AsteroidPosition x ="6.082008" y ="-49.50792" />
		<PerlinValue>0.1189033</PerlinValue>
	<AsteroidPosition x ="5.230085" y ="-49.24531" />
		<PerlinValue>0.1501786</PerlinValue>
	<AsteroidPosition x ="5.642442" y ="-48.76878" />
		<PerlinValue>0.2088531</PerlinValue>
	<AsteroidPosition x ="6.646182" y ="-48.2414" />
		<PerlinValue>0.2763092</PerlinValue>
	<AsteroidPosition x ="5.051291" y ="-46.44957" />
		<PerlinValue>0.3446885</PerlinValue>
	<AsteroidPosition x ="5.814014" y ="-45.57868" />
		<PerlinValue>0.2719453</PerlinValue>
	<AsteroidPosition x ="6.279762" y ="-43.42385" />
		<PerlinValue>0.2120232</PerlinValue>
	<AsteroidPosition x ="6.756184" y ="-34.13229" />
		<PerlinValue>0</PerlinValue>
	<AsteroidPosition x ="6.182487" y ="-34.12997" />
		<PerlinValue>0</PerlinValue>
	<AsteroidPosition x ="5.467398" y ="-32.15702" />
		<PerlinValue>0</PerlinValue>
	<AsteroidPosition x ="5.726859" y ="-31.90541" />
		<PerlinValue>0</PerlinValue>
	<AsteroidPosition x ="5.335615" y ="-29.61699" />
		<PerlinValue>0</PerlinValue>
	<AsteroidPosition x ="6.546926" y ="-29.27927" />
		<PerlinValue>0</PerlinValue>
	<AsteroidPosition x ="5.042222" y ="-27.91625" />
		<PerlinValue>0.3671766</PerlinValue>
	<AsteroidPosition x ="6.411405" y ="-28.34198" />
		<PerlinValue>0.2368826</PerlinValue>
	<AsteroidPosition x ="6.558459" y ="-51.29372" />
		<PerlinValue>0.1288885</PerlinValue>
	<AsteroidPosition x ="7.530012" y ="-51.10236" />
		<PerlinValue>0.06334257</PerlinValue>
	<AsteroidPosition x ="6.166529" y ="-48.91932" />
		<PerlinValue>0.04815987</PerlinValue>
	<AsteroidPosition x ="7.092048" y ="-48.60548" />
		<PerlinValue>0.07790017</PerlinValue>
	<AsteroidPosition x ="7.180722" y ="-47.21376" />
		<PerlinValue>0.1363831</PerlinValue>
	<AsteroidPosition x ="6.214479" y ="-45.59525" />
		<PerlinValue>0.2041239</PerlinValue>
	<AsteroidPosition x ="6.908674" y ="-46.37099" />
		<PerlinValue>0.2764845</PerlinValue>
	<AsteroidPosition x ="6.133251" y ="-44.76851" />
		<PerlinValue>0.2103606</PerlinValue>
	<AsteroidPosition x ="6.35677" y ="-34.45876" />
		<PerlinValue>0</PerlinValue>
	<AsteroidPosition x ="6.668429" y ="-33.76726" />
		<PerlinValue>0</PerlinValue>
	<AsteroidPosition x ="7.792303" y ="-32.26503" />
		<PerlinValue>0</PerlinValue>
	<AsteroidPosition x ="7.489086" y ="-28.42364" />
		<PerlinValue>0</PerlinValue>
	<AsteroidPosition x ="7.313188" y ="-28.35782" />
		<PerlinValue>0.3188598</PerlinValue>
	<AsteroidPosition x ="6.916814" y ="-51.76641" />
		<PerlinValue>0.1849544</PerlinValue>
	<AsteroidPosition x ="8.190059" y ="-51.3381" />
		<PerlinValue>0.07806564</PerlinValue>
	<AsteroidPosition x ="7.95911" y ="-48.77389" />
		<PerlinValue>0</PerlinValue>
	<AsteroidPosition x ="6.822116" y ="-49.03253" />
		<PerlinValue>0</PerlinValue>
	<AsteroidPosition x ="7.891437" y ="-47.48954" />
		<PerlinValue>0</PerlinValue>
	<AsteroidPosition x ="7.746998" y ="-46.59437" />
		<PerlinValue>0.1022998</PerlinValue>
	<AsteroidPosition x ="8.635059" y ="-44.67397" />
		<PerlinValue>0.1704053</PerlinValue>
	<AsteroidPosition x ="7.888677" y ="-44.41812" />
		<PerlinValue>0.247064</PerlinValue>
	<AsteroidPosition x ="8.078636" y ="-36.38716" />
		<PerlinValue>0</PerlinValue>
	<AsteroidPosition x ="8.748917" y ="-34.35699" />
		<PerlinValue>0</PerlinValue>
	<AsteroidPosition x ="7.165109" y ="-32.82061" />
		<PerlinValue>0</PerlinValue>
	<AsteroidPosition x ="8.68606" y ="-33.15503" />
		<PerlinValue>0</PerlinValue>
	<AsteroidPosition x ="7.616961" y ="-30.20404" />
		<PerlinValue>0</PerlinValue>
	<AsteroidPosition x ="7.059203" y ="-28.59558" />
		<PerlinValue>0</PerlinValue>
	<AsteroidPosition x ="8.236359" y ="-26.41602" />
		<PerlinValue>0.3930648</PerlinValue>
	<AsteroidPosition x ="9.430779" y ="-50.83942" />
		<PerlinValue>0.2619434</PerlinValue>
	<AsteroidPosition x ="9.445174" y ="-49.88523" />
		<PerlinValue>0.1375938</PerlinValue>
	<AsteroidPosition x ="8.798365" y ="-50.1538" />
		<PerlinValue>0.04602206</PerlinValue>
	<AsteroidPosition x ="9.310888" y ="-48.11967" />
		<PerlinValue>0</PerlinValue>
	<AsteroidPosition x ="8.856489" y ="-47.48053" />
		<PerlinValue>0</PerlinValue>
	<AsteroidPosition x ="8.818418" y ="-46.07633" />
		<PerlinValue>0.05354249</PerlinValue>
	<AsteroidPosition x ="9.100508" y ="-45.44426" />
		<PerlinValue>0.117096</PerlinValue>
	<AsteroidPosition x ="8.341551" y ="-43.77231" />
		<PerlinValue>0.1855769</PerlinValue>
	<AsteroidPosition x ="8.269251" y ="-35.68987" />
		<PerlinValue>0.378553</PerlinValue>
	<AsteroidPosition x ="9.565403" y ="-34.73545" />
		<PerlinValue>0</PerlinValue>
	<AsteroidPosition x ="8.124783" y ="-33.89378" />
		<PerlinValue>0</PerlinValue>
	<AsteroidPosition x ="8.368783" y ="-30.24332" />
		<PerlinValue>0</PerlinValue>
	<AsteroidPosition x ="8.107328" y ="-29.20773" />
		<PerlinValue>0</PerlinValue>
	<AsteroidPosition x ="9.614255" y ="-28.8488" />
		<PerlinValue>0</PerlinValue>
	<AsteroidPosition x ="8.88934" y ="-26.6213" />
		<PerlinValue>0</PerlinValue>
	<AsteroidPosition x ="8.972204" y ="-51.51986" />
		<PerlinValue>0.3299388</PerlinValue>
	<AsteroidPosition x ="10.10425" y ="-50.36259" />
		<PerlinValue>0.209497</PerlinValue>
	<AsteroidPosition x ="10.37217" y ="-48.67864" />
		<PerlinValue>0.1048687</PerlinValue>
	<AsteroidPosition x ="9.72616" y ="-49.29722" />
		<PerlinValue>0</PerlinValue>
	<AsteroidPosition x ="9.332592" y ="-47.06449" />
		<PerlinValue>0</PerlinValue>
	<AsteroidPosition x ="9.598508" y ="-45.88628" />
		<PerlinValue>0.05039852</PerlinValue>
	<AsteroidPosition x ="10.19182" y ="-45.5786" />
		<PerlinValue>0.1082774</PerlinValue>
	<AsteroidPosition x ="9.435684" y ="-36.0739" />
		<PerlinValue>0.312316</PerlinValue>
	<AsteroidPosition x ="10.25274" y ="-34.47992" />
		<PerlinValue>0.3662801</PerlinValue>
	<AsteroidPosition x ="10.74299" y ="-34.70539" />
		<PerlinValue>0</PerlinValue>
	<AsteroidPosition x ="9.820285" y ="-33.47027" />
		<PerlinValue>0</PerlinValue>
	<AsteroidPosition x ="9.060913" y ="-33.25143" />
		<PerlinValue>0</PerlinValue>
	<AsteroidPosition x ="9.112713" y ="-31.6764" />
		<PerlinValue>0</PerlinValue>
	<AsteroidPosition x ="9.727885" y ="-31.07786" />
		<PerlinValue>0</PerlinValue>
	<AsteroidPosition x ="10.26733" y ="-28.55606" />
		<PerlinValue>0</PerlinValue>
	<AsteroidPosition x ="10.09239" y ="-28.68775" />
		<PerlinValue>0</PerlinValue>
	<AsteroidPosition x ="9.06565" y ="-26.41589" />
		<PerlinValue>0</PerlinValue>
	<AsteroidPosition x ="11.49599" y ="-50.70707" />
		<PerlinValue>0.3828977</PerlinValue>
	<AsteroidPosition x ="10.46028" y ="-49.46572" />
		<PerlinValue>0.2789974</PerlinValue>
	<AsteroidPosition x ="11.6024" y ="-49.65274" />
		<PerlinValue>0.1737403</PerlinValue>
	<AsteroidPosition x ="11.2849" y ="-47.67566" />
		<PerlinValue>0.09286404</PerlinValue>
	<AsteroidPosition x ="9.896172" y ="-47.09352" />
		<PerlinValue>0.05538015</PerlinValue>
	<AsteroidPosition x ="10.74189" y ="-45.5696" />
		<PerlinValue>0.06679811</PerlinValue>
	<AsteroidPosition x ="10.02046" y ="-36.93628" />
		<PerlinValue>0.3784397</PerlinValue>
	<AsteroidPosition x ="10.55118" y ="-36.39156" />
		<PerlinValue>0.3978222</PerlinValue>
	<AsteroidPosition x ="9.83334" y ="-34.59774" />
		<PerlinValue>0</PerlinValue>
	<AsteroidPosition x ="9.94008" y ="-33.10907" />
		<PerlinValue>0</PerlinValue>
	<AsteroidPosition x ="10.28838" y ="-31.72784" />
		<PerlinValue>0</PerlinValue>
	<AsteroidPosition x ="10.20597" y ="-30.86519" />
		<PerlinValue>0</PerlinValue>
	<AsteroidPosition x ="10.14499" y ="-30.25791" />
		<PerlinValue>0</PerlinValue>
	<AsteroidPosition x ="10.41487" y ="-30.25992" />
		<PerlinValue>0</PerlinValue>
	<AsteroidPosition x ="11.0104" y ="-28.67315" />
		<PerlinValue>0</PerlinValue>
	<AsteroidPosition x ="11.70436" y ="-50.61952" />
		<PerlinValue>0</PerlinValue>
	<AsteroidPosition x ="11.97897" y ="-36.77753" />
		<PerlinValue>0</PerlinValue>
	<AsteroidPosition x ="11.59713" y ="-35.77728" />
		<PerlinValue>0</PerlinValue>
	<AsteroidPosition x ="11.00941" y ="-33.96742" />
		<PerlinValue>0</PerlinValue>
	<AsteroidPosition x ="11.94787" y ="-33.78003" />
		<PerlinValue>0</PerlinValue>
	<AsteroidPosition x ="10.97519" y ="-31.54333" />
		<PerlinValue>0</PerlinValue>
	<AsteroidPosition x ="12.6286" y ="-30.71524" />
		<PerlinValue>0</PerlinValue>
	<AsteroidPosition x ="12.14287" y ="-30.68152" />
		<PerlinValue>0</PerlinValue>
	<AsteroidPosition x ="11.48005" y ="-28.5486" />
		<PerlinValue>0</PerlinValue>
	<AsteroidPosition x ="12.94137" y ="-36.12634" />
		<PerlinValue>0</PerlinValue>
	<AsteroidPosition x ="12.28864" y ="-35.26917" />
		<PerlinValue>0</PerlinValue>
	<AsteroidPosition x ="12.50656" y ="-35.14505" />
		<PerlinValue>0</PerlinValue>
	<AsteroidPosition x ="12.60856" y ="-34.02776" />
		<PerlinValue>0</PerlinValue>
	<AsteroidPosition x ="12.31829" y ="-32.79406" />
		<PerlinValue>0</PerlinValue>
	<AsteroidPosition x ="11.87114" y ="-31.09787" />
		<PerlinValue>0</PerlinValue>
	<AsteroidPosition x ="13.52706" y ="-30.28913" />
		<PerlinValue>0</PerlinValue>
	<AsteroidPosition x ="14.04494" y ="-35.43511" />
		<PerlinValue>0</PerlinValue>
	<AsteroidPosition x ="13.32907" y ="-35.73769" />
		<PerlinValue>0</PerlinValue>
	<AsteroidPosition x ="14.31569" y ="-35.3399" />
		<PerlinValue>0</PerlinValue>
	<AsteroidPosition x ="13.52094" y ="-32.45977" />
		<PerlinValue>0</PerlinValue>
	<AsteroidPosition x ="12.89293" y ="-32.52099" />
		<PerlinValue>0</PerlinValue>
	<AsteroidPosition x ="14.29821" y ="-30.72455" />
		<PerlinValue>0</PerlinValue>
	<AsteroidPosition x ="14.44415" y ="-31.32354" />
		<PerlinValue>0</PerlinValue>
	<AsteroidPosition x ="14.36562" y ="-35.89276" />
		<PerlinValue>0</PerlinValue>
	<AsteroidPosition x ="15.30436" y ="-35.49339" />
		<PerlinValue>0</PerlinValue>
	<AsteroidPosition x ="14.07159" y ="-34.66615" />
		<PerlinValue>0</PerlinValue>
	<AsteroidPosition x ="14.40613" y ="-32.91798" />
		<PerlinValue>0</PerlinValue>
	<AsteroidPosition x ="14.29894" y ="-31.60532" />
		<PerlinValue>0</PerlinValue>
	<AsteroidPosition x ="15.11516" y ="-31.3321" />
		<PerlinValue>0</PerlinValue>
	<AsteroidPosition x ="14.10534" y ="-31.17692" />
		<PerlinValue>0</PerlinValue>
	<AsteroidPosition x ="15.93147" y ="-35.98287" />
		<PerlinValue>0</PerlinValue>
	<AsteroidPosition x ="16.10439" y ="-33.64051" />
		<PerlinValue>0</PerlinValue>
	<AsteroidPosition x ="14.98804" y ="-33.20102" />
		<PerlinValue>0</PerlinValue>
	<AsteroidPosition x ="15.43428" y ="-31.69089" />
		<PerlinValue>0</PerlinValue>
	<AsteroidPosition x ="15.99995" y ="-30.67127" />
		<PerlinValue>0</PerlinValue>
	<AsteroidPosition x ="15.48308" y ="-30.98871" />
		<PerlinValue>0</PerlinValue>
	<AsteroidPosition x ="16.40518" y ="-35.39275" />
		<PerlinValue>0</PerlinValue>
	<AsteroidPosition x ="17.68167" y ="-33.78449" />
		<PerlinValue>0</PerlinValue>
	<AsteroidPosition x ="16.83296" y ="-33.40021" />
		<PerlinValue>0</PerlinValue>
	<AsteroidPosition x ="16.56231" y ="-32.4036" />
		<PerlinValue>0</PerlinValue>
	<AsteroidPosition x ="16.62613" y ="-32.14484" />
		<PerlinValue>0</PerlinValue>
	<AsteroidPosition x ="17.56448" y ="-30.51805" />
		<PerlinValue>0</PerlinValue>
	<AsteroidPosition x ="15.80631" y ="-28.45263" />
		<PerlinValue>0</PerlinValue>
	<AsteroidPosition x ="17.80342" y ="-34.67578" />
		<PerlinValue>0</PerlinValue>
	<AsteroidPosition x ="17.0663" y ="-32.6413" />
		<PerlinValue>0</PerlinValue>
	<AsteroidPosition x ="18.74365" y ="-32.1476" />
		<PerlinValue>0</PerlinValue>
	<AsteroidPosition x ="16.89605" y ="-31.53902" />
		<PerlinValue>0</PerlinValue>
	<AsteroidPosition x ="18.14419" y ="-30.311" />
		<PerlinValue>0</PerlinValue>
	<AsteroidPosition x ="17.0975" y ="-29.23307" />
		<PerlinValue>0</PerlinValue>
	<AsteroidPosition x ="17.98382" y ="-27.64235" />
		<PerlinValue>0</PerlinValue>
	<AsteroidPosition x ="19.37102" y ="-33.94431" />
		<PerlinValue>0</PerlinValue>
	<AsteroidPosition x ="18.94674" y ="-31.77239" />
		<PerlinValue>0</PerlinValue>
	<AsteroidPosition x ="19.01056" y ="-32.30427" />
		<PerlinValue>0</PerlinValue>
	<AsteroidPosition x ="19.50193" y ="-29.7561" />
		<PerlinValue>0</PerlinValue>
	<AsteroidPosition x ="18.026" y ="-28.5182" />
		<PerlinValue>0</PerlinValue>
	<AsteroidPosition x ="18.2223" y ="-29.15876" />
		<PerlinValue>0</PerlinValue>
	<AsteroidPosition x ="19.84826" y ="-51.64706" />
		<PerlinValue>0</PerlinValue>
	<AsteroidPosition x ="19.93123" y ="-49.62869" />
		<PerlinValue>0</PerlinValue>
	<AsteroidPosition x ="19.83001" y ="-40.89753" />
		<PerlinValue>0</PerlinValue>
	<AsteroidPosition x ="19.55935" y ="-39.21758" />
		<PerlinValue>0.3836012</PerlinValue>
	<AsteroidPosition x ="20.66085" y ="-32.00241" />
		<PerlinValue>0</PerlinValue>
	<AsteroidPosition x ="18.95773" y ="-32.05991" />
		<PerlinValue>0.3833584</PerlinValue>
	<AsteroidPosition x ="19.0662" y ="-31.00405" />
		<PerlinValue>0.3928218</PerlinValue>
	<AsteroidPosition x ="19.17048" y ="-29.60489" />
		<PerlinValue>0</PerlinValue>
	<AsteroidPosition x ="20.46072" y ="-27.45266" />
		<PerlinValue>0</PerlinValue>
	<AsteroidPosition x ="21.2256" y ="-51.33797" />
		<PerlinValue>0</PerlinValue>
	<AsteroidPosition x ="21.10381" y ="-50.31739" />
		<PerlinValue>0</PerlinValue>
	<AsteroidPosition x ="20.39428" y ="-48.80229" />
		<PerlinValue>0</PerlinValue>
	<AsteroidPosition x ="21.6737" y ="-42.04882" />
		<PerlinValue>0</PerlinValue>
	<AsteroidPosition x ="20.23639" y ="-40.19209" />
		<PerlinValue>0</PerlinValue>
	<AsteroidPosition x ="21.11555" y ="-38.79692" />
		<PerlinValue>0</PerlinValue>
	<AsteroidPosition x ="19.90227" y ="-31.62853" />
		<PerlinValue>0</PerlinValue>
	<AsteroidPosition x ="20.84979" y ="-31.96854" />
		<PerlinValue>0</PerlinValue>
	<AsteroidPosition x ="20.15743" y ="-29.66052" />
		<PerlinValue>0.3731082</PerlinValue>
	<AsteroidPosition x ="19.84316" y ="-28.5318" />
		<PerlinValue>0.3673185</PerlinValue>
	<AsteroidPosition x ="20.69867" y ="-28.10261" />
		<PerlinValue>0.3932166</PerlinValue>
	<AsteroidPosition x ="21.70848" y ="-51.26119" />
		<PerlinValue>0</PerlinValue>
	<AsteroidPosition x ="22.18402" y ="-50.33276" />
		<PerlinValue>0</PerlinValue>
	<AsteroidPosition x ="22.13" y ="-49.60339" />
		<PerlinValue>0</PerlinValue>
	<AsteroidPosition x ="21.11698" y ="-42.39021" />
		<PerlinValue>0</PerlinValue>
	<AsteroidPosition x ="21.93472" y ="-41.1306" />
		<PerlinValue>0</PerlinValue>
	<AsteroidPosition x ="21.3453" y ="-38.4529" />
		<PerlinValue>0</PerlinValue>
	<AsteroidPosition x ="22.43269" y ="-31.33226" />
		<PerlinValue>0</PerlinValue>
	<AsteroidPosition x ="21.70601" y ="-31.1375" />
		<PerlinValue>0</PerlinValue>
	<AsteroidPosition x ="22.69334" y ="-29.02245" />
		<PerlinValue>0.3813294</PerlinValue>
	<AsteroidPosition x ="22.3101" y ="-50.48997" />
		<PerlinValue>0</PerlinValue>
	<AsteroidPosition x ="23.06674" y ="-49.70092" />
		<PerlinValue>0</PerlinValue>
	<AsteroidPosition x ="22.97968" y ="-49.17539" />
		<PerlinValue>0</PerlinValue>
	<AsteroidPosition x ="23.23215" y ="-40.95533" />
		<PerlinValue>0</PerlinValue>
	<AsteroidPosition x ="23.44539" y ="-41.02441" />
		<PerlinValue>0</PerlinValue>
	<AsteroidPosition x ="23.42329" y ="-39.21135" />
		<PerlinValue>0</PerlinValue>
	<AsteroidPosition x ="24.34394" y ="-51.09506" />
		<PerlinValue>0.384079</PerlinValue>
	<AsteroidPosition x ="24.77926" y ="-49.52946" />
		<PerlinValue>0</PerlinValue>
	<AsteroidPosition x ="23.06936" y ="-48.487" />
		<PerlinValue>0</PerlinValue>
	<AsteroidPosition x ="24.79265" y ="-42.19425" />
		<PerlinValue>0.3828978</PerlinValue>
	<AsteroidPosition x ="23.04626" y ="-39.47554" />
		<PerlinValue>0</PerlinValue>
	<AsteroidPosition x ="24.32705" y ="-39.73502" />
		<PerlinValue>0</PerlinValue>
</Root>